odoo8_addon_l10n_it_causali_pagamento-8.0.2.0.0-nspkg.pth
odoo_addons/l10n_it_causali_pagamento/README.rst
odoo_addons/l10n_it_causali_pagamento/__init__.py
odoo_addons/l10n_it_causali_pagamento/__openerp__.py
odoo_addons/l10n_it_causali_pagamento/data/causali_pagamento_data.xml
odoo_addons/l10n_it_causali_pagamento/i18n/it.po
odoo_addons/l10n_it_causali_pagamento/i18n/l10n_it_causali_pagamento.pot
odoo_addons/l10n_it_causali_pagamento/migrations/8.0.1.1.0/post-migrate.py
odoo_addons/l10n_it_causali_pagamento/models/__init__.py
odoo_addons/l10n_it_causali_pagamento/models/causale_pagamento.py
odoo_addons/l10n_it_causali_pagamento/readme/CONFIGURE.rst
odoo_addons/l10n_it_causali_pagamento/readme/CONTRIBUTORS.rst
odoo_addons/l10n_it_causali_pagamento/readme/DESCRIPTION.rst
odoo_addons/l10n_it_causali_pagamento/readme/USAGE.rst
odoo_addons/l10n_it_causali_pagamento/security/ir.model.access.csv
odoo_addons/l10n_it_causali_pagamento/static/description/icon.png
odoo_addons/l10n_it_causali_pagamento/static/description/index.html
odoo_addons/l10n_it_causali_pagamento/tests/__init__.py
odoo_addons/l10n_it_causali_pagamento/tests/test_causali.py
odoo_addons/l10n_it_causali_pagamento/views/causali_pagamento_view.xml
odoo8_addon_l10n_it_causali_pagamento-8.0.2.0.0.dist-info/METADATA
odoo8_addon_l10n_it_causali_pagamento-8.0.2.0.0.dist-info/WHEEL
odoo8_addon_l10n_it_causali_pagamento-8.0.2.0.0.dist-info/namespace_packages.txt
odoo8_addon_l10n_it_causali_pagamento-8.0.2.0.0.dist-info/top_level.txt
odoo8_addon_l10n_it_causali_pagamento-8.0.2.0.0.dist-info/RECORD
